image/__init__.py
image/apps.py
image/fields.py
image/forms.py
image/misc.py
image/models.py
image/settings.py
image/storage.py
image/urls.py
image/utils.py
image/video_field.py
image/videothumbs.py
image/views.py
image/templatetags/__init__.py
image/templatetags/img.py
image-1.5.27.dist-info/DESCRIPTION.rst
image-1.5.27.dist-info/METADATA
image-1.5.27.dist-info/RECORD
image-1.5.27.dist-info/WHEEL
image-1.5.27.dist-info/metadata.json
image-1.5.27.dist-info/top_level.txt
